{
  "version": "1.0.0",
  "last_updated": "2025-01-27T22:30:00Z",
  "created_by": "Claude Sonnet 4 - Sonnet 4",
  "converted_from": "E:\\kos\\ai-Q\\agents\\handoff\\MODULAR_REGISTRY_IMPLEMENTATION_GUIDE.json",
  "conversion_timestamp": "2025-01-27T22:30:00Z",
  "converter": "RobustYAMLToJSONConverter v1.0",
  "purpose": "Converted from problematic YAML file: MODULAR_REGISTRY_IMPLEMENTATION_GUIDE.json",
  "title": "Modular Registry Implementation Guide",
  "original_content": "# MODULAR COMPONENT REGISTRY IMPLEMENTATION GUIDE\n# TOKEN COUNT: ~12,000 tokens\n---\nversion: \"1.0.0\"\nlast_updated: \"2025-01-27T15:00:00Z\"\ncreated_by: \"Claude Sonnet 4\"\npurpose: >\n  Detailed implementation guide for the modular component registry system that enables\n  true \"lego-like\" architecture where components can be discovered, loaded, and composed\n  without code duplication.\n\n# IMPLEMENTATION OVERVIEW\nimplementation_overview:\n  goal: \"Create a comprehensive component registry system that eliminates code duplication\"\n  principle: \"Write once, use everywhere - no duplicate code across recipes\"\n  architecture: \"Dynamic component discovery and loading with dependency resolution\"\n  success_criteria:\n    - \"Zero code duplication across recipes\"\n    - \"Components can be discovered and loaded dynamically\"\n    - \"Dependencies resolved automatically\"\n    - \"Components are truly reusable without modification\"\n    - \"Registry provides comprehensive metadata and documentation\"\n\n# CORE REGISTRY ARCHITECTURE\nregistry_architecture:\n  registry_core:\n    purpose: \"Central component management and discovery\"\n    components:\n      - \"ComponentRegistry - Main registry class\"\n      - \"ComponentLoader - Dynamic loading engine\"\n      - \"DependencyResolver - Dependency management\"\n      - \"ComponentValidator - Validation and testing\"\n      - \"ComponentMetadata - Metadata management\"\n    \n    file_structure:\n      - \"src/registry/__init__.py\"\n      - \"src/registry/core.py - Main registry implementation\"\n      - \"src/registry/loader.py - Component loading\"\n      - \"src/registry/dependencies.py - Dependency resolution\"\n      - \"src/registry/validation.py - Component validation\"\n      - \"src/registry/metadata.py - Metadata management\"\n      - \"src/registry/discovery.py - Component discovery\"\n  \n  component_interface:\n    purpose: \"Standard interface all components must implement\"\n    interface_contract:\n      - \"init() - Component initialization\"\n      - \"configure(config) - Configuration setup\"\n      - \"validate() - Self-validation\"\n      - \"test() - Self-testing\"\n      - \"cleanup() - Resource cleanup\"\n      - \"get_metadata() - Return component metadata\"\n    \n    base_component_class:\n      - \"AbstractComponent - Base class for all components\"\n      - \"ComponentConfig - Configuration schema\"\n      - \"ComponentMetadata - Metadata schema\"\n      - \"ComponentError - Error handling\"\n  \n  component_categories:\n    authentication:\n      description: \"Authentication and authorization components\"\n      components:\n        - \"oauth2-provider\"\n        - \"jwt-manager\"\n        - \"rbac-engine\"\n        - \"mfa-handler\"\n        - \"sso-provider\"\n        - \"permission-manager\"\n      \n      common_interface:\n        - \"authenticate(credentials) - Authenticate user\"\n        - \"authorize(user, resource) - Check permissions\"\n        - \"create_token(user) - Generate tokens\"\n        - \"validate_token(token) - Validate tokens\"\n    \n    storage:\n      description: \"Data storage and management components\"\n      components:\n        - \"file-storage-manager\"\n        - \"database-connector\"\n        - \"cache-manager\"\n        - \"backup-service\"\n        - \"migration-manager\"\n        - \"storage-monitor\"\n      \n      common_interface:\n        - \"store(key, data) - Store data\"\n        - \"retrieve(key) - Retrieve data\"\n        - \"delete(key) - Delete data\"\n        - \"list(prefix) - List data\"\n        - \"backup() - Create backup\"\n    \n    processing:\n      description: \"Data processing and transformation components\"\n      components:\n        - \"text-processor\"\n        - \"image-processor\"\n        - \"video-processor\"\n        - \"audio-processor\"\n        - \"document-processor\"\n        - \"code-processor\"\n      \n      common_interface:\n        - \"process(input_data) - Process data\"\n        - \"extract_features(data) - Extract features\"\n        - \"transform(data, format) - Transform data\"\n        - \"validate_output(output) - Validate output\"\n    \n    ai_ml:\n      description: \"AI and machine learning components\"\n      components:\n        - \"embedding-engine\"\n        - \"rag-processor\"\n        - \"semantic-searcher\"\n        - \"knowledge-graph\"\n        - \"model-manager\"\n        - \"training-pipeline\"\n      \n      common_interface:\n        - \"embed(data) - Generate embeddings\"\n        - \"search(query) - Perform search\"\n        - \"generate(context) - Generate content\"\n        - \"train(data) - Train models\"\n    \n    api:\n      description: \"API and communication components\"\n      components:\n        - \"rest-api-builder\"\n        - \"graphql-schema\"\n        - \"grpc-service\"\n        - \"websocket-handler\"\n        - \"rate-limiter\"\n        - \"api-documentation\"\n      \n      common_interface:\n        - \"create_endpoint(path, handler) - Create endpoint\"\n        - \"handle_request(request) - Handle request\"\n        - \"validate_request(request) - Validate request\"\n        - \"format_response(response) - Format response\"\n    \n    ui:\n      description: \"User interface components\"\n      components:\n        - \"component-library\"\n        - \"dashboard-builder\"\n        - \"form-generator\"\n        - \"chart-renderer\"\n        - \"theme-manager\"\n        - \"responsive-layout\"\n      \n      common_interface:\n        - \"render(data) - Render component\"\n        - \"update(data) - Update component\"\n        - \"handle_event(event) - Handle events\"\n        - \"get_styles() - Get styles\"\n    \n    hardware:\n      description: \"Hardware detection and management components\"\n      components:\n        - \"gpu-detector\"\n        - \"memory-monitor\"\n        - \"network-analyzer\"\n        - \"robotics-interface\"\n        - \"sensor-manager\"\n        - \"actuator-controller\"\n      \n      common_interface:\n        - \"detect() - Detect hardware\"\n        - \"monitor() - Monitor status\"\n        - \"control(device, action) - Control device\"\n        - \"get_capabilities() - Get capabilities\"\n\n# IMPLEMENTATION STEPS\nimplementation_steps:\n  step_1_registry_core:\n    priority: \"CRITICAL\"\n    duration: \"3-4 days\"\n    description: \"Implement core registry functionality\"\n    \n    tasks:\n      - \"Create src/registry/ directory structure\"\n      - \"Implement ComponentRegistry class\"\n      - \"Implement component registration system\"\n      - \"Implement component discovery system\"\n      - \"Create base Component interface\"\n      - \"Implement metadata management\"\n    \n    files_to_create:\n      - \"src/registry/__init__.py\"\n      - \"src/registry/core.py\"\n      - \"src/registry/interface.py\"\n      - \"src/registry/metadata.py\"\n      - \"tests/registry/test_core.py\"\n    \n    acceptance_criteria:\n      - \"Components can be registered with metadata\"\n      - \"Components can be discovered by category\"\n      - \"Component metadata is properly managed\"\n      - \"Registry provides search functionality\"\n      - \"All tests pass\"\n  \n  step_2_dependency_resolution:\n    priority: \"CRITICAL\"\n    duration: \"2-3 days\"\n    description: \"Implement dependency resolution system\"\n    \n    tasks:\n      - \"Implement DependencyResolver class\"\n      - \"Create dependency graph management\"\n      - \"Implement circular dependency detection\"\n      - \"Create dependency loading order\"\n      - \"Implement dependency validation\"\n    \n    files_to_create:\n      - \"src/registry/dependencies.py\"\n      - \"src/registry/graph.py\"\n      - \"tests/registry/test_dependencies.py\"\n    \n    acceptance_criteria:\n      - \"Dependencies are resolved correctly\"\n      - \"Circular dependencies are detected\"\n      - \"Loading order is optimal\"\n      - \"Dependency conflicts are resolved\"\n      - \"All tests pass\"\n  \n  step_3_component_loading:\n    priority: \"HIGH\"\n    duration: \"2-3 days\"\n    description: \"Implement dynamic component loading\"\n    \n    tasks:\n      - \"Implement ComponentLoader class\"\n      - \"Create lazy loading mechanism\"\n      - \"Implement component instantiation\"\n      - \"Create component lifecycle management\"\n      - \"Implement hot-swapping capability\"\n    \n    files_to_create:\n      - \"src/registry/loader.py\"\n      - \"src/registry/lifecycle.py\"\n      - \"tests/registry/test_loader.py\"\n    \n    acceptance_criteria:\n      - \"Components load dynamically\"\n      - \"Lazy loading works correctly\"\n      - \"Component lifecycle is managed\"\n      - \"Hot-swapping works safely\"\n      - \"All tests pass\"\n  \n  step_4_validation_system:\n    priority: \"HIGH\"\n    duration: \"2-3 days\"\n    description: \"Implement component validation and testing\"\n    \n    tasks:\n      - \"Implement ComponentValidator class\"\n      - \"Create interface validation\"\n      - \"Implement self-testing framework\"\n      - \"Create performance validation\"\n      - \"Implement security validation\"\n    \n    files_to_create:\n      - \"src/registry/validation.py\"\n      - \"src/registry/testing.py\"\n      - \"tests/registry/test_validation.py\"\n    \n    acceptance_criteria:\n      - \"Components are validated on registration\"\n      - \"Self-tests run automatically\"\n      - \"Performance benchmarks are tracked\"\n      - \"Security checks are performed\"\n      - \"All tests pass\"\n  \n  step_5_core_components:\n    priority: \"HIGH\"\n    duration: \"1 week\"\n    description: \"Implement core reusable components\"\n    \n    tasks:\n      - \"Implement authentication components\"\n      - \"Implement storage components\"\n      - \"Implement basic API components\"\n      - \"Create component examples\"\n      - \"Write component documentation\"\n    \n    files_to_create:\n      - \"src/components/auth/__init__.py\"\n      - \"src/components/auth/oauth2_provider.py\"\n      - \"src/components/auth/jwt_manager.py\"\n      - \"src/components/storage/__init__.py\"\n      - \"src/components/storage/file_manager.py\"\n      - \"src/components/storage/database_connector.py\"\n      - \"src/components/api/__init__.py\"\n      - \"src/components/api/rest_builder.py\"\n      - \"examples/auth_example.py\"\n      - \"examples/storage_example.py\"\n      - \"docs/components/auth.md\"\n      - \"docs/components/storage.md\"\n    \n    acceptance_criteria:\n      - \"All core components work correctly\"\n      - \"Components are truly reusable\"\n      - \"Examples demonstrate usage\"\n      - \"Documentation is comprehensive\"\n      - \"All tests pass\"\n  \n  step_6_ai_components:\n    priority: \"MEDIUM\"\n    duration: \"1 week\"\n    description: \"Implement AI/ML components\"\n    \n    tasks:\n      - \"Implement RAG engine component\"\n      - \"Implement semantic search component\"\n      - \"Implement embedding engine\"\n      - \"Create AI pipeline components\"\n      - \"Write AI component documentation\"\n    \n    files_to_create:\n      - \"src/components/ai/__init__.py\"\n      - \"src/components/ai/rag_engine.py\"\n      - \"src/components/ai/semantic_searcher.py\"\n      - \"src/components/ai/embedding_engine.py\"\n      - \"src/components/ai/knowledge_graph.py\"\n      - \"examples/ai_example.py\"\n      - \"docs/components/ai.md\"\n    \n    acceptance_criteria:\n      - \"AI components work correctly\"\n      - \"Components integrate with each other\"\n      - \"Performance is acceptable\"\n      - \"Documentation is clear\"\n      - \"All tests pass\"\n  \n  step_7_hardware_components:\n    priority: \"MEDIUM\"\n    duration: \"1 week\"\n    description: \"Implement hardware detection components\"\n    \n    tasks:\n      - \"Implement GPU detection component\"\n      - \"Implement memory monitoring\"\n      - \"Implement network analysis\"\n      - \"Create robotics interface\"\n      - \"Write hardware documentation\"\n    \n    files_to_create:\n      - \"src/components/hardware/__init__.py\"\n      - \"src/components/hardware/gpu_detector.py\"\n      - \"src/components/hardware/memory_monitor.py\"\n      - \"src/components/hardware/network_analyzer.py\"\n      - \"src/components/hardware/robotics_interface.py\"\n      - \"examples/hardware_example.py\"\n      - \"docs/components/hardware.md\"\n    \n    acceptance_criteria:\n      - \"Hardware detection works correctly\"\n      - \"Monitoring is real-time\"\n      - \"Robotics interface is extensible\"\n      - \"Documentation is comprehensive\"\n      - \"All tests pass\"\n  \n  step_8_ui_components:\n    priority: \"MEDIUM\"\n    duration: \"1 week\"\n    description: \"Implement UI components\"\n    \n    tasks:\n      - \"Implement component library\"\n      - \"Create dashboard builder\"\n      - \"Implement form generator\"\n      - \"Create chart renderer\"\n      - \"Write UI documentation\"\n    \n    files_to_create:\n      - \"src/components/ui/__init__.py\"\n      - \"src/components/ui/component_library.py\"\n      - \"src/components/ui/dashboard_builder.py\"\n      - \"src/components/ui/form_generator.py\"\n      - \"src/components/ui/chart_renderer.py\"\n      - \"examples/ui_example.py\"\n      - \"docs/components/ui.md\"\n    \n    acceptance_criteria:\n      - \"UI components render correctly\"\n      - \"Components are responsive\"\n      - \"Theme system works\"\n      - \"Documentation is clear\"\n      - \"All tests pass\"\n\n# COMPONENT REGISTRY USAGE PATTERNS\nusage_patterns:\n  recipe_implementation:\n    pattern: \"Discover and use existing components\"\n    steps:\n      - \"Check registry for existing components\"\n      - \"Load required components\"\n      - \"Configure components for recipe needs\"\n      - \"Compose components into recipe\"\n      - \"No code duplication\"\n    \n    example:\n      - \"Recipe needs authentication\"\n      - \"Check registry: oauth2-provider available\"\n      - \"Load oauth2-provider component\"\n      - \"Configure with recipe-specific settings\"\n      - \"Use component without modification\"\n  \n  component_composition:\n    pattern: \"Combine multiple components\"\n    steps:\n      - \"Load multiple components\"\n      - \"Configure inter-component communication\"\n      - \"Create composition layer\"\n      - \"Expose unified interface\"\n    \n    example:\n      - \"Need file upload with processing\"\n      - \"Load file-storage-manager\"\n      - \"Load text-processor\"\n      - \"Create composition that stores then processes\"\n      - \"Expose unified upload_and_process() method\"\n  \n  dynamic_loading:\n    pattern: \"Load components based on conditions\"\n    steps:\n      - \"Check system capabilities\"\n      - \"Load appropriate components\"\n      - \"Fallback to alternatives if needed\"\n    \n    example:\n      - \"Check if GPU available\"\n      - \"Load gpu-accelerated-ai if available\"\n      - \"Fallback to cpu-ai if not\"\n      - \"Same interface, different implementation\n\n# QUALITY ASSURANCE PROCESS\nquality_assurance:\n  recursive_review_process:\n    description: \"Multi-level review with full file context\"\n    \n    level_1_code_review:\n      - \"Read entire file before making changes\"\n      - \"Trace logic flow completely\"\n      - \"Check for missing imports\"\n      - \"Verify no duplicate code\"\n      - \"Ensure generic, reusable design\"\n    \n    level_2_integration_review:\n      - \"Check component interactions\"\n      - \"Verify dependency resolution\"\n      - \"Test component composition\"\n      - \"Validate error handling\"\n      - \"Check performance impact\"\n    \n    level_3_system_review:\n      - \"Verify system-wide consistency\"\n      - \"Check for architectural violations\"\n      - \"Validate security implications\"\n      - \"Test scalability concerns\"\n      - \"Review documentation completeness\"\n  \n  validation_checkpoints:\n    after_component_creation:\n      - \"Component follows interface contract\"\n      - \"Component has comprehensive tests\"\n      - \"Component is documented\"\n      - \"Component is generic and reusable\"\n      - \"No duplicate functionality exists\"\n    \n    after_integration:\n      - \"Components work together\"\n      - \"Dependencies resolved correctly\"\n      - \"Performance is acceptable\"\n      - \"Error handling works\"\n      - \"Documentation is updated\"\n    \n    before_deployment:\n      - \"All tests pass\"\n      - \"No critical issues\"\n      - \"Performance benchmarks met\"\n      - \"Security review complete\"\n      - \"Documentation complete\"\n\n# SUCCESS METRICS\nsuccess_metrics:\n  technical_metrics:\n    - \"Zero code duplication across recipes\"\n    - \"Component discovery time < 100ms\"\n    - \"Component loading time < 200ms\"\n    - \"Dependency resolution time < 50ms\"\n    - \"100% component test coverage\"\n    - \"All components follow interface contract\"\n  \n  quality_metrics:\n    - \"All components are truly reusable\"\n    - \"No monolithic implementations\"\n    - \"Clear separation of concerns\"\n    - \"Comprehensive error handling\"\n    - \"Complete documentation coverage\"\n    - \"No technical debt accumulation\"\n  \n  productivity_metrics:\n    - \"Recipe implementation time reduced by 80%\"\n    - \"Component reuse rate > 90%\"\n    - \"Developer productivity increased by 60%\"\n    - \"Bug rate reduced by 70%\"\n    - \"Maintenance time reduced by 50%\"\n\n# CONCLUSION\nconclusion: >\n  The modular component registry system is the foundation for achieving the AI-Q vision\n  of a true \"lego-like\" architecture. By implementing this system, the next agent will\n  enable recipes to discover and use existing components without duplication, creating\n  a highly maintainable and scalable system that can support the universal digital twin\n  and robotics integration goals. Success depends on following the recursive review\n  process, maintaining zero technical debt, and building truly generic, reusable\n  components that can be composed into complex systems without modification. ",
  "conversion_notes": "This file had YAML syntax errors and was converted to basic JSON structure",
  "requires_manual_review": true,
  "extracted_data": {
    "version": "\"1.0.0\"",
    "last_updated": "\"2025-01-27T15:00:00Z\"",
    "created_by": "\"Claude Sonnet 4\"",
    "purpose": "\"Standard interface all components must implement\"",
    "goal": "\"Create a comprehensive component registry system that eliminates code duplication\"",
    "principle": "\"Write once, use everywhere - no duplicate code across recipes\"",
    "architecture": "\"Dynamic component discovery and loading with dependency resolution\"",
    "success_criteria": [
      "\"Zero code duplication across recipes\"",
      "\"Components can be discovered and loaded dynamically\"",
      "\"Dependencies resolved automatically\"",
      "\"Components are truly reusable without modification\"",
      "\"Registry provides comprehensive metadata and documentation\""
    ],
    "components": [
      "\"ComponentRegistry - Main registry class\"",
      "\"ComponentLoader - Dynamic loading engine\"",
      "\"DependencyResolver - Dependency management\"",
      "\"ComponentValidator - Validation and testing\"",
      "\"ComponentMetadata - Metadata management\"",
      "\"oauth2-provider\"",
      "\"jwt-manager\"",
      "\"rbac-engine\"",
      "\"mfa-handler\"",
      "\"sso-provider\"",
      "\"permission-manager\"",
      "\"file-storage-manager\"",
      "\"database-connector\"",
      "\"cache-manager\"",
      "\"backup-service\"",
      "\"migration-manager\"",
      "\"storage-monitor\"",
      "\"text-processor\"",
      "\"image-processor\"",
      "\"video-processor\"",
      "\"audio-processor\"",
      "\"document-processor\"",
      "\"code-processor\"",
      "\"embedding-engine\"",
      "\"rag-processor\"",
      "\"semantic-searcher\"",
      "\"knowledge-graph\"",
      "\"model-manager\"",
      "\"training-pipeline\"",
      "\"rest-api-builder\"",
      "\"graphql-schema\"",
      "\"grpc-service\"",
      "\"websocket-handler\"",
      "\"rate-limiter\"",
      "\"api-documentation\"",
      "\"component-library\"",
      "\"dashboard-builder\"",
      "\"form-generator\"",
      "\"chart-renderer\"",
      "\"theme-manager\"",
      "\"responsive-layout\"",
      "\"gpu-detector\"",
      "\"memory-monitor\"",
      "\"network-analyzer\"",
      "\"robotics-interface\"",
      "\"sensor-manager\"",
      "\"actuator-controller\""
    ],
    "file_structure": [
      "\"src/registry/__init__.py\"",
      "\"src/registry/core.py - Main registry implementation\"",
      "\"src/registry/loader.py - Component loading\"",
      "\"src/registry/dependencies.py - Dependency resolution\"",
      "\"src/registry/validation.py - Component validation\"",
      "\"src/registry/metadata.py - Metadata management\"",
      "\"src/registry/discovery.py - Component discovery\""
    ],
    "interface_contract": [
      "\"init() - Component initialization\"",
      "\"configure(config) - Configuration setup\"",
      "\"validate() - Self-validation\"",
      "\"test() - Self-testing\"",
      "\"cleanup() - Resource cleanup\"",
      "\"get_metadata() - Return component metadata\""
    ],
    "base_component_class": [
      "\"AbstractComponent - Base class for all components\"",
      "\"ComponentConfig - Configuration schema\"",
      "\"ComponentMetadata - Metadata schema\"",
      "\"ComponentError - Error handling\""
    ],
    "description": "\"Multi-level review with full file context\"",
    "common_interface": [
      "\"authenticate(credentials) - Authenticate user\"",
      "\"authorize(user, resource) - Check permissions\"",
      "\"create_token(user) - Generate tokens\"",
      "\"validate_token(token) - Validate tokens\"",
      "\"store(key, data) - Store data\"",
      "\"retrieve(key) - Retrieve data\"",
      "\"delete(key) - Delete data\"",
      "\"list(prefix) - List data\"",
      "\"backup() - Create backup\"",
      "\"process(input_data) - Process data\"",
      "\"extract_features(data) - Extract features\"",
      "\"transform(data, format) - Transform data\"",
      "\"validate_output(output) - Validate output\"",
      "\"embed(data) - Generate embeddings\"",
      "\"search(query) - Perform search\"",
      "\"generate(context) - Generate content\"",
      "\"train(data) - Train models\"",
      "\"create_endpoint(path, handler) - Create endpoint\"",
      "\"handle_request(request) - Handle request\"",
      "\"validate_request(request) - Validate request\"",
      "\"format_response(response) - Format response\"",
      "\"render(data) - Render component\"",
      "\"update(data) - Update component\"",
      "\"handle_event(event) - Handle events\"",
      "\"get_styles() - Get styles\"",
      "\"detect() - Detect hardware\"",
      "\"monitor() - Monitor status\"",
      "\"control(device, action) - Control device\"",
      "\"get_capabilities() - Get capabilities\""
    ],
    "priority": "\"MEDIUM\"",
    "duration": "\"1 week\"",
    "tasks": [
      "\"Create src/registry/ directory structure\"",
      "\"Implement ComponentRegistry class\"",
      "\"Implement component registration system\"",
      "\"Implement component discovery system\"",
      "\"Create base Component interface\"",
      "\"Implement metadata management\"",
      "\"Implement DependencyResolver class\"",
      "\"Create dependency graph management\"",
      "\"Implement circular dependency detection\"",
      "\"Create dependency loading order\"",
      "\"Implement dependency validation\"",
      "\"Implement ComponentLoader class\"",
      "\"Create lazy loading mechanism\"",
      "\"Implement component instantiation\"",
      "\"Create component lifecycle management\"",
      "\"Implement hot-swapping capability\"",
      "\"Implement ComponentValidator class\"",
      "\"Create interface validation\"",
      "\"Implement self-testing framework\"",
      "\"Create performance validation\"",
      "\"Implement security validation\"",
      "\"Implement authentication components\"",
      "\"Implement storage components\"",
      "\"Implement basic API components\"",
      "\"Create component examples\"",
      "\"Write component documentation\"",
      "\"Implement RAG engine component\"",
      "\"Implement semantic search component\"",
      "\"Implement embedding engine\"",
      "\"Create AI pipeline components\"",
      "\"Write AI component documentation\"",
      "\"Implement GPU detection component\"",
      "\"Implement memory monitoring\"",
      "\"Implement network analysis\"",
      "\"Create robotics interface\"",
      "\"Write hardware documentation\"",
      "\"Implement component library\"",
      "\"Create dashboard builder\"",
      "\"Implement form generator\"",
      "\"Create chart renderer\"",
      "\"Write UI documentation\""
    ],
    "files_to_create": [
      "\"src/registry/__init__.py\"",
      "\"src/registry/core.py\"",
      "\"src/registry/interface.py\"",
      "\"src/registry/metadata.py\"",
      "\"tests/registry/test_core.py\"",
      "\"src/registry/dependencies.py\"",
      "\"src/registry/graph.py\"",
      "\"tests/registry/test_dependencies.py\"",
      "\"src/registry/loader.py\"",
      "\"src/registry/lifecycle.py\"",
      "\"tests/registry/test_loader.py\"",
      "\"src/registry/validation.py\"",
      "\"src/registry/testing.py\"",
      "\"tests/registry/test_validation.py\"",
      "\"src/components/auth/__init__.py\"",
      "\"src/components/auth/oauth2_provider.py\"",
      "\"src/components/auth/jwt_manager.py\"",
      "\"src/components/storage/__init__.py\"",
      "\"src/components/storage/file_manager.py\"",
      "\"src/components/storage/database_connector.py\"",
      "\"src/components/api/__init__.py\"",
      "\"src/components/api/rest_builder.py\"",
      "\"examples/auth_example.py\"",
      "\"examples/storage_example.py\"",
      "\"docs/components/auth.md\"",
      "\"docs/components/storage.md\"",
      "\"src/components/ai/__init__.py\"",
      "\"src/components/ai/rag_engine.py\"",
      "\"src/components/ai/semantic_searcher.py\"",
      "\"src/components/ai/embedding_engine.py\"",
      "\"src/components/ai/knowledge_graph.py\"",
      "\"examples/ai_example.py\"",
      "\"docs/components/ai.md\"",
      "\"src/components/hardware/__init__.py\"",
      "\"src/components/hardware/gpu_detector.py\"",
      "\"src/components/hardware/memory_monitor.py\"",
      "\"src/components/hardware/network_analyzer.py\"",
      "\"src/components/hardware/robotics_interface.py\"",
      "\"examples/hardware_example.py\"",
      "\"docs/components/hardware.md\"",
      "\"src/components/ui/__init__.py\"",
      "\"src/components/ui/component_library.py\"",
      "\"src/components/ui/dashboard_builder.py\"",
      "\"src/components/ui/form_generator.py\"",
      "\"src/components/ui/chart_renderer.py\"",
      "\"examples/ui_example.py\"",
      "\"docs/components/ui.md\""
    ],
    "acceptance_criteria": [
      "\"Components can be registered with metadata\"",
      "\"Components can be discovered by category\"",
      "\"Component metadata is properly managed\"",
      "\"Registry provides search functionality\"",
      "\"All tests pass\"",
      "\"Dependencies are resolved correctly\"",
      "\"Circular dependencies are detected\"",
      "\"Loading order is optimal\"",
      "\"Dependency conflicts are resolved\"",
      "\"All tests pass\"",
      "\"Components load dynamically\"",
      "\"Lazy loading works correctly\"",
      "\"Component lifecycle is managed\"",
      "\"Hot-swapping works safely\"",
      "\"All tests pass\"",
      "\"Components are validated on registration\"",
      "\"Self-tests run automatically\"",
      "\"Performance benchmarks are tracked\"",
      "\"Security checks are performed\"",
      "\"All tests pass\"",
      "\"All core components work correctly\"",
      "\"Components are truly reusable\"",
      "\"Examples demonstrate usage\"",
      "\"Documentation is comprehensive\"",
      "\"All tests pass\"",
      "\"AI components work correctly\"",
      "\"Components integrate with each other\"",
      "\"Performance is acceptable\"",
      "\"Documentation is clear\"",
      "\"All tests pass\"",
      "\"Hardware detection works correctly\"",
      "\"Monitoring is real-time\"",
      "\"Robotics interface is extensible\"",
      "\"Documentation is comprehensive\"",
      "\"All tests pass\"",
      "\"UI components render correctly\"",
      "\"Components are responsive\"",
      "\"Theme system works\"",
      "\"Documentation is clear\"",
      "\"All tests pass\""
    ],
    "pattern": "\"Load components based on conditions\"",
    "steps": [
      "\"Check registry for existing components\"",
      "\"Load required components\"",
      "\"Configure components for recipe needs\"",
      "\"Compose components into recipe\"",
      "\"No code duplication\"",
      "\"Load multiple components\"",
      "\"Configure inter-component communication\"",
      "\"Create composition layer\"",
      "\"Expose unified interface\"",
      "\"Check system capabilities\"",
      "\"Load appropriate components\"",
      "\"Fallback to alternatives if needed\""
    ],
    "example": [
      "\"Recipe needs authentication\"",
      "\"Check registry: oauth2-provider available\"",
      "\"Load oauth2-provider component\"",
      "\"Configure with recipe-specific settings\"",
      "\"Use component without modification\"",
      "\"Need file upload with processing\"",
      "\"Load file-storage-manager\"",
      "\"Load text-processor\"",
      "\"Create composition that stores then processes\"",
      "\"Expose unified upload_and_process() method\"",
      "\"Check if GPU available\"",
      "\"Load gpu-accelerated-ai if available\"",
      "\"Fallback to cpu-ai if not\"",
      "\"Same interface, different implementation"
    ],
    "level_1_code_review": [
      "\"Read entire file before making changes\"",
      "\"Trace logic flow completely\"",
      "\"Check for missing imports\"",
      "\"Verify no duplicate code\"",
      "\"Ensure generic, reusable design\""
    ],
    "level_2_integration_review": [
      "\"Check component interactions\"",
      "\"Verify dependency resolution\"",
      "\"Test component composition\"",
      "\"Validate error handling\"",
      "\"Check performance impact\""
    ],
    "level_3_system_review": [
      "\"Verify system-wide consistency\"",
      "\"Check for architectural violations\"",
      "\"Validate security implications\"",
      "\"Test scalability concerns\"",
      "\"Review documentation completeness\""
    ],
    "after_component_creation": [
      "\"Component follows interface contract\"",
      "\"Component has comprehensive tests\"",
      "\"Component is documented\"",
      "\"Component is generic and reusable\"",
      "\"No duplicate functionality exists\""
    ],
    "after_integration": [
      "\"Components work together\"",
      "\"Dependencies resolved correctly\"",
      "\"Performance is acceptable\"",
      "\"Error handling works\"",
      "\"Documentation is updated\""
    ],
    "before_deployment": [
      "\"All tests pass\"",
      "\"No critical issues\"",
      "\"Performance benchmarks met\"",
      "\"Security review complete\"",
      "\"Documentation complete\""
    ],
    "technical_metrics": [
      "\"Zero code duplication across recipes\"",
      "\"Component discovery time < 100ms\"",
      "\"Component loading time < 200ms\"",
      "\"Dependency resolution time < 50ms\"",
      "\"100% component test coverage\"",
      "\"All components follow interface contract\""
    ],
    "quality_metrics": [
      "\"All components are truly reusable\"",
      "\"No monolithic implementations\"",
      "\"Clear separation of concerns\"",
      "\"Comprehensive error handling\"",
      "\"Complete documentation coverage\"",
      "\"No technical debt accumulation\""
    ],
    "productivity_metrics": [
      "\"Recipe implementation time reduced by 80%\"",
      "\"Component reuse rate > 90%\"",
      "\"Developer productivity increased by 60%\"",
      "\"Bug rate reduced by 70%\"",
      "\"Maintenance time reduced by 50%\""
    ],
    "conclusion": ">"
  }
}