{
  "version": "1.0.0",
  "last_updated": "2025-01-27T22:30:00Z",
  "created_by": "Claude Sonnet 4 - Sonnet 4",
  "converted_from": "E:\\kos\\ai-Q\\agents\\analysis\\ERROR_ANALYSIS_REPORT.json",
  "conversion_timestamp": "2025-01-27T22:30:00Z",
  "converter": "RobustYAMLToJSONConverter v1.0",
  "purpose": "Converted from problematic YAML file: ERROR_ANALYSIS_REPORT.json",
  "title": "Error Analysis Report",
  "original_content": "# ERROR ANALYSIS REPORT - AI-Q KNOWLEDGE LIBRARY SYSTEM\n# COMPREHENSIVE REVIEW OF ALL PREVIOUS WORK\n# TOKEN COUNT: ~4,500 tokens\n---\nversion: \"1.0.0\"\nlast_updated: \"2025-01-27T22:00:00Z\"\ncreated_by: \"Claude Sonnet 4 - Claude Sonnet 4\"\npurpose: >\n  Comprehensive error analysis report documenting all issues found in the current\n  AI-Q implementation, following the critical assumption that the previous agent\n  made errors. This report serves as the foundation for all fixes and improvements.\n\n# EXECUTIVE SUMMARY\nexecutive_summary:\n  total_issues_found: 15\n  critical_issues: 8\n  high_priority_issues: 4\n  medium_priority_issues: 3\n  low_priority_issues: 0\n  overall_assessment: \"REQUIRES SIGNIFICANT OVERHAUL\"\n  estimated_fix_time: \"8-12 hours\"\n\n# CRITICAL ISSUES (IMMEDIATE FIXES REQUIRED)\n\n## ISSUE 1: MISSING .ENV FILE\nseverity: \"Critical\"\ndescription: \"No .env file exists in the project root\"\nimpact: \"Environment configuration cannot be loaded, system cannot start\"\nlocation: \"Project root directory\"\nfiles_affected:\n  - \"src/config/env-parser.ts\"\n  - \"src/config/file-loader.ts\"\n  - \"All components expecting environment variables\"\ndetails:\n  - \"env-parser.ts expects .env file for environment variables\"\n  - \"file-loader.ts expects environment-template.json (exists but may not be used)\"\n  - \"No fallback mechanism for missing .env file\"\n  - \"System cannot start without environment configuration\"\nresolution:\n  - \"Create .env file with all required environment variables\"\n  - \"Use environment-template.json as template\"\n  - \"Add fallback mechanisms for missing environment variables\"\n  - \"Implement environment validation\"\n\n## ISSUE 2: CONFIGURATION INTERFACE INCONSISTENCY\nseverity: \"Critical\"\ndescription: \"Configuration interfaces are consistent but implementation is incomplete\"\nimpact: \"Type safety maintained but runtime functionality compromised\"\nlocation: \"src/config/\"\nfiles_affected:\n  - \"src/config/types.ts\"\n  - \"src/config/env-parser.ts\"\n  - \"src/config/file-loader.ts\"\ndetails:\n  - \"types.ts defines comprehensive EnvironmentConfig interface\"\n  - \"env-parser.ts correctly implements the interface\"\n  - \"file-loader.ts correctly uses the interface\"\n  - \"However, no actual configuration loading mechanism is implemented\"\nresolution:\n  - \"Implement configuration loading mechanism\"\n  - \"Add configuration validation\"\n  - \"Create configuration manager class\"\n  - \"Add error handling for configuration loading\"\n\n## ISSUE 3: MISSING MAIN ENTRY POINT IMPLEMENTATION\nseverity: \"Critical\"\ndescription: \"Main entry points exist but are not properly implemented\"\nimpact: \"System cannot start or run\"\nlocation: \"src/\"\nfiles_affected:\n  - \"src/index.ts\"\n  - \"src/main.py\"\ndetails:\n  - \"index.ts exists but implementation is incomplete\"\n  - \"main.py exists but implementation is incomplete\"\n  - \"No proper startup sequence\"\n  - \"No error handling for startup failures\"\nresolution:\n  - \"Complete main entry point implementations\"\n  - \"Add proper startup sequence\"\n  - \"Implement error handling\"\n  - \"Add logging and monitoring\"\n\n## ISSUE 4: MISSING TEST INFRASTRUCTURE\nseverity: \"Critical\"\ndescription: \"No testing framework or test files implemented\"\nimpact: \"Cannot validate functionality, violates zero technical debt policy\"\nlocation: \"Project root\"\nfiles_affected:\n  - \"All source files\"\n  - \"No test directory exists\"\ndetails:\n  - \"No test framework setup\"\n  - \"No unit test files\"\n  - \"No integration test files\"\n  - \"No test utilities or helpers\"\n  - \"No test configuration\"\nresolution:\n  - \"Set up comprehensive testing framework\"\n  - \"Create unit tests for all components\"\n  - \"Create integration tests\"\n  - \"Add test utilities and helpers\"\n  - \"Configure test environment\"\n\n## ISSUE 5: MISSING DEPENDENCY MANAGEMENT\nseverity: \"Critical\"\ndescription: \"Dependencies not properly managed or installed\"\nimpact: \"System cannot build or run\"\nlocation: \"Project root\"\nfiles_affected:\n  - \"package.json\"\n  - \"requirements.txt\"\n  - \"All source files\"\ndetails:\n  - \"Node.js dependencies may not be installed\"\n  - \"Python dependencies may not be installed\"\n  - \"Virtual environment may not be set up\"\n  - \"Build tools may not be configured\"\nresolution:\n  - \"Install all Node.js dependencies\"\n  - \"Set up Python virtual environment\"\n  - \"Install all Python dependencies\"\n  - \"Verify build process\"\n  - \"Test all dependencies\"\n\n## ISSUE 6: MISSING DOCUMENTATION STANDARDS\nseverity: \"Critical\"\ndescription: \"Inconsistent documentation patterns across files\"\nimpact: \"Maintenance difficult, violates documentation standards\"\nlocation: \"All source files\"\nfiles_affected:\n  - \"All .ts files\"\n  - \"All .py files\"\n  - \"All .json files\"\ndetails:\n  - \"Some files have detailed headers, others don't\"\n  - \"Missing JSDoc comments in TypeScript files\"\n  - \"Inconsistent token count metadata\"\n  - \"Missing purpose and usage documentation\"\nresolution:\n  - \"Standardize documentation across all files\"\n  - \"Add JSDoc comments to all TypeScript files\"\n  - \"Add consistent headers to all files\"\n  - \"Update token count metadata\"\n  - \"Add usage documentation\"\n\n## ISSUE 7: MISSING ERROR HANDLING\nseverity: \"Critical\"\ndescription: \"Incomplete error handling across components\"\nimpact: \"System failures not properly handled, debugging difficult\"\nlocation: \"All source files\"\nfiles_affected:\n  - \"All source files\"\ndetails:\n  - \"Some functions don't handle errors\"\n  - \"Inconsistent error message formats\"\n  - \"Missing error logging\"\n  - \"No error recovery mechanisms\"\nresolution:\n  - \"Implement comprehensive error handling\"\n  - \"Standardize error message formats\"\n  - \"Add error logging\"\n  - \"Implement error recovery mechanisms\"\n\n## ISSUE 8: MISSING BUILD AND DEPLOYMENT CONFIGURATION\nseverity: \"Critical\"\ndescription: \"Build and deployment configuration incomplete\"\nimpact: \"Cannot build or deploy the system\"\nlocation: \"Project root\"\nfiles_affected:\n  - \"package.json\"\n  - \"tsconfig.json\"\n  - \"next.config.js\"\n  - \"docker-compose.json\"\ndetails:\n  - \"Build scripts may not be properly configured\"\n  - \"TypeScript configuration may be incomplete\"\n  - \"Docker configuration may be incomplete\"\n  - \"Deployment scripts missing\"\nresolution:\n  - \"Complete build configuration\"\n  - \"Fix TypeScript configuration\"\n  - \"Complete Docker configuration\"\n  - \"Add deployment scripts\"\n\n# HIGH PRIORITY ISSUES\n\n## ISSUE 9: MISSING USER STORIES\nseverity: \"High\"\ndescription: \"No comprehensive user story analysis completed\"\nimpact: \"System may not meet user needs\"\nlocation: \"Project planning\"\nfiles_affected:\n  - \"All system design decisions\"\ndetails:\n  - \"No user stories generated\"\n  - \"No user journey maps\"\n  - \"No use case analysis\"\n  - \"No requirement analysis\"\nresolution:\n  - \"Generate comprehensive user stories\"\n  - \"Create user journey maps\"\n  - \"Analyze use cases\"\n  - \"Document requirements\"\n\n## ISSUE 10: MISSING RECIPE SYSTEM VALIDATION\nseverity: \"High\"\ndescription: \"Recipe system exists but not validated for context window optimization\"\nimpact: \"Recipes may not be optimal for AI agent execution\"\nlocation: \"recipes/\"\nfiles_affected:\n  - \"All recipe files\"\ndetails:\n  - \"Recipes may be too large for context windows\"\n  - \"No validation of recipe efficiency\"\n  - \"No testing of recipe execution\"\n  - \"No optimization for AI agent consumption\"\nresolution:\n  - \"Validate recipe sizes for context windows\"\n  - \"Optimize recipes for AI agent execution\"\n  - \"Test recipe execution\"\n  - \"Implement recipe validation\"\n\n## ISSUE 11: MISSING GRANULAR IMPLEMENTATION PLAN\nseverity: \"High\"\ndescription: \"No detailed task breakdown with small steps\"\nimpact: \"Blocks systematic development\"\nlocation: \"Project planning\"\nfiles_affected:\n  - \"All implementation tasks\"\ndetails:\n  - \"No granular task breakdown\"\n  - \"No dependency mapping\"\n  - \"No effort estimation\"\n  - \"No resource allocation\"\nresolution:\n  - \"Create detailed task breakdown\"\n  - \"Map dependencies\"\n  - \"Estimate effort\"\n  - \"Allocate resources\"\n\n## ISSUE 12: MISSING QUALITY ASSURANCE FRAMEWORK\nseverity: \"High\"\ndescription: \"No quality assurance framework implemented\"\nimpact: \"Risk of poor quality deliverables\"\nlocation: \"Project management\"\nfiles_affected:\n  - \"All deliverables\"\ndetails:\n  - \"No quality standards defined\"\n  - \"No quality checks implemented\"\n  - \"No quality metrics\"\n  - \"No quality reporting\"\nresolution:\n  - \"Define quality standards\"\n  - \"Implement quality checks\"\n  - \"Define quality metrics\"\n  - \"Create quality reporting\"\n\n# MEDIUM PRIORITY ISSUES\n\n## ISSUE 13: MISSING MONITORING AND LOGGING\nseverity: \"Medium\"\ndescription: \"No comprehensive monitoring and logging system\"\nimpact: \"Difficult to debug and maintain\"\nlocation: \"System infrastructure\"\nfiles_affected:\n  - \"All system components\"\ndetails:\n  - \"No logging framework\"\n  - \"No monitoring system\"\n  - \"No alerting mechanism\"\n  - \"No performance tracking\"\nresolution:\n  - \"Implement logging framework\"\n  - \"Set up monitoring system\"\n  - \"Configure alerting\"\n  - \"Add performance tracking\"\n\n## ISSUE 14: MISSING SECURITY FRAMEWORK\nseverity: \"Medium\"\ndescription: \"No comprehensive security framework implemented\"\nimpact: \"Security vulnerabilities possible\"\nlocation: \"System security\"\nfiles_affected:\n  - \"All system components\"\ndetails:\n  - \"No authentication system\"\n  - \"No authorization framework\"\n  - \"No security validation\"\n  - \"No security monitoring\"\nresolution:\n  - \"Implement authentication system\"\n  - \"Set up authorization framework\"\n  - \"Add security validation\"\n  - \"Implement security monitoring\"\n\n## ISSUE 15: MISSING PERFORMANCE OPTIMIZATION\nseverity: \"Medium\"\ndescription: \"No performance optimization implemented\"\nimpact: \"System may not meet performance requirements\"\nlocation: \"System performance\"\nfiles_affected:\n  - \"All system components\"\ndetails:\n  - \"No performance benchmarks\"\n  - \"No performance monitoring\"\n  - \"No optimization strategies\"\n  - \"No performance testing\"\nresolution:\n  - \"Define performance benchmarks\"\n  - \"Implement performance monitoring\"\n  - \"Apply optimization strategies\"\n  - \"Add performance testing\"\n\n# IMMEDIATE ACTION PLAN\n\n## PHASE 1: CRITICAL FIXES (IMMEDIATE - 4-6 hours)\npriority: \"Critical\"\nactions:\n  1: \"Create .env file\"\n    - \"Use environment-template.json as template\"\n    - \"Add all required environment variables\"\n    - \"Validate environment configuration\"\n  \n  2: \"Complete main entry point implementations\"\n    - \"Finish index.ts implementation\"\n    - \"Finish main.py implementation\"\n    - \"Add proper startup sequence\"\n    - \"Add error handling\"\n  \n  3: \"Set up testing infrastructure\"\n    - \"Install testing frameworks\"\n    - \"Create test directory structure\"\n    - \"Write initial test files\"\n    - \"Configure test environment\"\n  \n  4: \"Fix dependency management\"\n    - \"Install Node.js dependencies\"\n    - \"Set up Python virtual environment\"\n    - \"Install Python dependencies\"\n    - \"Verify build process\"\n\n## PHASE 2: HIGH PRIORITY FIXES (HIGH - 2-3 hours)\npriority: \"High\"\nactions:\n  1: \"Generate user stories\"\n    - \"Analyze all user categories\"\n    - \"Generate 100+ user stories\"\n    - \"Create user journey maps\"\n    - \"Document requirements\"\n  \n  2: \"Validate recipe system\"\n    - \"Check recipe sizes\"\n    - \"Optimize for context windows\"\n    - \"Test recipe execution\"\n    - \"Implement validation\"\n  \n  3: \"Create granular implementation plan\"\n    - \"Break down all tasks\"\n    - \"Map dependencies\"\n    - \"Estimate effort\"\n    - \"Allocate resources\"\n\n## PHASE 3: MEDIUM PRIORITY FIXES (MEDIUM - 2-3 hours)\npriority: \"Medium\"\nactions:\n  1: \"Implement monitoring and logging\"\n    - \"Set up logging framework\"\n    - \"Configure monitoring\"\n    - \"Add alerting\"\n    - \"Track performance\"\n  \n  2: \"Implement security framework\"\n    - \"Add authentication\"\n    - \"Set up authorization\"\n    - \"Add security validation\"\n    - \"Monitor security\"\n  \n  3: \"Implement quality assurance\"\n    - \"Define quality standards\"\n    - \"Add quality checks\"\n    - \"Create quality metrics\"\n    - \"Set up quality reporting\"\n\n# SUCCESS CRITERIA\nsuccess_criteria:\n  technical:\n    - \"All critical issues resolved\"\n    - \"System can start and run without errors\"\n    - \"All tests passing with production data\"\n    - \"All dependencies properly managed\"\n    - \"Build process working correctly\"\n  \n  quality:\n    - \"All documentation standardized\"\n    - \"Error handling comprehensive\"\n    - \"Quality assurance framework implemented\"\n    - \"Monitoring and logging active\"\n  \n  operational:\n    - \"User stories generated and validated\"\n    - \"Recipe system optimized\"\n    - \"Implementation plan detailed\"\n    - \"Security framework implemented\"\n\n# CONCLUSION\nconclusion: >\n  The current AI-Q implementation has 15 significant issues that must be resolved\n  before the system can function properly. The most critical issues are missing\n  environment configuration, incomplete main entry points, and missing testing\n  infrastructure. These must be addressed immediately to prevent further development\n  delays and ensure system stability.\n  \n  All fixes must follow zero technical debt principles and use production-only\n  testing as specified in the project standards. The estimated time to resolve\n  all issues is 8-12 hours, with critical fixes requiring 4-6 hours immediately.\n  \n  This report serves as the foundation for all subsequent fixes and improvements\n  to the AI-Q Knowledge Library System. ",
  "conversion_notes": "This file had YAML syntax errors and was converted to basic JSON structure",
  "requires_manual_review": true,
  "extracted_data": {
    "version": "\"1.0.0\"",
    "last_updated": "\"2025-01-27T22:00:00Z\"",
    "created_by": "\"Claude Sonnet 4 - Claude Sonnet 4\"",
    "purpose": ">",
    "total_issues_found": "15",
    "critical_issues": "8",
    "high_priority_issues": "4",
    "medium_priority_issues": "3",
    "low_priority_issues": "0",
    "overall_assessment": "\"REQUIRES SIGNIFICANT OVERHAUL\"",
    "estimated_fix_time": "\"8-12 hours\"",
    "severity": "\"Medium\"",
    "description": "\"No performance optimization implemented\"",
    "impact": "\"System may not meet performance requirements\"",
    "location": "\"System performance\"",
    "files_affected": [
      "\"src/config/env-parser.ts\"",
      "\"src/config/file-loader.ts\"",
      "\"All components expecting environment variables\"",
      "\"src/config/types.ts\"",
      "\"src/config/env-parser.ts\"",
      "\"src/config/file-loader.ts\"",
      "\"src/index.ts\"",
      "\"src/main.py\"",
      "\"All source files\"",
      "\"No test directory exists\"",
      "\"package.json\"",
      "\"requirements.txt\"",
      "\"All source files\"",
      "\"All .ts files\"",
      "\"All .py files\"",
      "\"All .json files\"",
      "\"All source files\"",
      "\"package.json\"",
      "\"tsconfig.json\"",
      "\"next.config.js\"",
      "\"docker-compose.json\"",
      "\"All system design decisions\"",
      "\"All recipe files\"",
      "\"All implementation tasks\"",
      "\"All deliverables\"",
      "\"All system components\"",
      "\"All system components\"",
      "\"All system components\""
    ],
    "details": [
      "\"env-parser.ts expects .env file for environment variables\"",
      "\"file-loader.ts expects environment-template.json (exists but may not be used)\"",
      "\"No fallback mechanism for missing .env file\"",
      "\"System cannot start without environment configuration\"",
      "\"types.ts defines comprehensive EnvironmentConfig interface\"",
      "\"env-parser.ts correctly implements the interface\"",
      "\"file-loader.ts correctly uses the interface\"",
      "\"However, no actual configuration loading mechanism is implemented\"",
      "\"index.ts exists but implementation is incomplete\"",
      "\"main.py exists but implementation is incomplete\"",
      "\"No proper startup sequence\"",
      "\"No error handling for startup failures\"",
      "\"No test framework setup\"",
      "\"No unit test files\"",
      "\"No integration test files\"",
      "\"No test utilities or helpers\"",
      "\"No test configuration\"",
      "\"Node.js dependencies may not be installed\"",
      "\"Python dependencies may not be installed\"",
      "\"Virtual environment may not be set up\"",
      "\"Build tools may not be configured\"",
      "\"Some files have detailed headers, others don't\"",
      "\"Missing JSDoc comments in TypeScript files\"",
      "\"Inconsistent token count metadata\"",
      "\"Missing purpose and usage documentation\"",
      "\"Some functions don't handle errors\"",
      "\"Inconsistent error message formats\"",
      "\"Missing error logging\"",
      "\"No error recovery mechanisms\"",
      "\"Build scripts may not be properly configured\"",
      "\"TypeScript configuration may be incomplete\"",
      "\"Docker configuration may be incomplete\"",
      "\"Deployment scripts missing\"",
      "\"No user stories generated\"",
      "\"No user journey maps\"",
      "\"No use case analysis\"",
      "\"No requirement analysis\"",
      "\"Recipes may be too large for context windows\"",
      "\"No validation of recipe efficiency\"",
      "\"No testing of recipe execution\"",
      "\"No optimization for AI agent consumption\"",
      "\"No granular task breakdown\"",
      "\"No dependency mapping\"",
      "\"No effort estimation\"",
      "\"No resource allocation\"",
      "\"No quality standards defined\"",
      "\"No quality checks implemented\"",
      "\"No quality metrics\"",
      "\"No quality reporting\"",
      "\"No logging framework\"",
      "\"No monitoring system\"",
      "\"No alerting mechanism\"",
      "\"No performance tracking\"",
      "\"No authentication system\"",
      "\"No authorization framework\"",
      "\"No security validation\"",
      "\"No security monitoring\"",
      "\"No performance benchmarks\"",
      "\"No performance monitoring\"",
      "\"No optimization strategies\"",
      "\"No performance testing\""
    ],
    "resolution": [
      "\"Create .env file with all required environment variables\"",
      "\"Use environment-template.json as template\"",
      "\"Add fallback mechanisms for missing environment variables\"",
      "\"Implement environment validation\"",
      "\"Implement configuration loading mechanism\"",
      "\"Add configuration validation\"",
      "\"Create configuration manager class\"",
      "\"Add error handling for configuration loading\"",
      "\"Complete main entry point implementations\"",
      "\"Add proper startup sequence\"",
      "\"Implement error handling\"",
      "\"Add logging and monitoring\"",
      "\"Set up comprehensive testing framework\"",
      "\"Create unit tests for all components\"",
      "\"Create integration tests\"",
      "\"Add test utilities and helpers\"",
      "\"Configure test environment\"",
      "\"Install all Node.js dependencies\"",
      "\"Set up Python virtual environment\"",
      "\"Install all Python dependencies\"",
      "\"Verify build process\"",
      "\"Test all dependencies\"",
      "\"Standardize documentation across all files\"",
      "\"Add JSDoc comments to all TypeScript files\"",
      "\"Add consistent headers to all files\"",
      "\"Update token count metadata\"",
      "\"Add usage documentation\"",
      "\"Implement comprehensive error handling\"",
      "\"Standardize error message formats\"",
      "\"Add error logging\"",
      "\"Implement error recovery mechanisms\"",
      "\"Complete build configuration\"",
      "\"Fix TypeScript configuration\"",
      "\"Complete Docker configuration\"",
      "\"Add deployment scripts\"",
      "\"Generate comprehensive user stories\"",
      "\"Create user journey maps\"",
      "\"Analyze use cases\"",
      "\"Document requirements\"",
      "\"Validate recipe sizes for context windows\"",
      "\"Optimize recipes for AI agent execution\"",
      "\"Test recipe execution\"",
      "\"Implement recipe validation\"",
      "\"Create detailed task breakdown\"",
      "\"Map dependencies\"",
      "\"Estimate effort\"",
      "\"Allocate resources\"",
      "\"Define quality standards\"",
      "\"Implement quality checks\"",
      "\"Define quality metrics\"",
      "\"Create quality reporting\"",
      "\"Implement logging framework\"",
      "\"Set up monitoring system\"",
      "\"Configure alerting\"",
      "\"Add performance tracking\"",
      "\"Implement authentication system\"",
      "\"Set up authorization framework\"",
      "\"Add security validation\"",
      "\"Implement security monitoring\"",
      "\"Define performance benchmarks\"",
      "\"Implement performance monitoring\"",
      "\"Apply optimization strategies\"",
      "\"Add performance testing\""
    ],
    "priority": "\"Medium\"",
    "1": "\"Implement monitoring and logging\"",
    "actions": [
      "\"Use environment-template.json as template\"",
      "\"Add all required environment variables\"",
      "\"Validate environment configuration\"",
      "\"Finish index.ts implementation\"",
      "\"Finish main.py implementation\"",
      "\"Add proper startup sequence\"",
      "\"Add error handling\"",
      "\"Install testing frameworks\"",
      "\"Create test directory structure\"",
      "\"Write initial test files\"",
      "\"Configure test environment\"",
      "\"Install Node.js dependencies\"",
      "\"Set up Python virtual environment\"",
      "\"Install Python dependencies\"",
      "\"Verify build process\"",
      "\"Analyze all user categories\"",
      "\"Generate 100+ user stories\"",
      "\"Create user journey maps\"",
      "\"Document requirements\"",
      "\"Check recipe sizes\"",
      "\"Optimize for context windows\"",
      "\"Test recipe execution\"",
      "\"Implement validation\"",
      "\"Break down all tasks\"",
      "\"Map dependencies\"",
      "\"Estimate effort\"",
      "\"Allocate resources\"",
      "\"Set up logging framework\"",
      "\"Configure monitoring\"",
      "\"Add alerting\"",
      "\"Track performance\"",
      "\"Add authentication\"",
      "\"Set up authorization\"",
      "\"Add security validation\"",
      "\"Monitor security\"",
      "\"Define quality standards\"",
      "\"Add quality checks\"",
      "\"Create quality metrics\"",
      "\"Set up quality reporting\""
    ],
    "2": "\"Implement security framework\"",
    "3": "\"Implement quality assurance\"",
    "4": "\"Fix dependency management\"",
    "technical": [
      "\"All critical issues resolved\"",
      "\"System can start and run without errors\"",
      "\"All tests passing with production data\"",
      "\"All dependencies properly managed\"",
      "\"Build process working correctly\""
    ],
    "quality": [
      "\"All documentation standardized\"",
      "\"Error handling comprehensive\"",
      "\"Quality assurance framework implemented\"",
      "\"Monitoring and logging active\""
    ],
    "operational": [
      "\"User stories generated and validated\"",
      "\"Recipe system optimized\"",
      "\"Implementation plan detailed\"",
      "\"Security framework implemented\""
    ],
    "conclusion": ">"
  }
}